{
  "context": {
    "date": "2019-05-20 19:36:51",
    "host_name": "redwan",
    "executable": "./T_ASE_Benchmark",
    "num_cpus": 8,
    "mhz_per_cpu": 3700,
    "cpu_scaling_enabled": true,
    "caches": [
      {
        "type": "Data",
        "level": 1,
        "size": 32000000,
        "num_sharing": 2
      },
      {
        "type": "Instruction",
        "level": 1,
        "size": 32000000,
        "num_sharing": 2
      },
      {
        "type": "Unified",
        "level": 2,
        "size": 256000000,
        "num_sharing": 2
      },
      {
        "type": "Unified",
        "level": 3,
        "size": 6144000000,
        "num_sharing": 8
      },
      {
        "type": "Unified",
        "level": 4,
        "size": 131072000000,
        "num_sharing": 8
      }
    ],
    "load_avg": [2.18,2.28,2.33],
    "library_build_type": "release"
  },
  "benchmarks": [
    {
      "name": "MyFixture<double>/DpTest",
      "run_name": "MyFixture<double>/DpTest",
      "run_type": "iteration",
      "repetitions": 0,
      "repetition_index": 0,
      "threads": 1,
      "iterations": 1,
      "real_time": 3.3617340871919996e+13,
      "cpu_time": 3.3288016616999996e+10,
      "time_unit": "ns",
      "elapsed": 3.3279334280000000e+01
    },
    {
      "name": "MyFixture<double>/DpTest",
      "run_name": "MyFixture<double>/DpTest",
      "run_type": "iteration",
      "repetitions": 0,
      "repetition_index": 1,
      "threads": 1,
      "iterations": 1,
      "real_time": 3.3653850476522000e+13,
      "cpu_time": 6.9796243118000000e+10,
      "time_unit": "ns",
      "elapsed": 3.6504790919999998e+01
    },
    {
      "name": "MyFixture<double>/DpTest",
      "run_name": "MyFixture<double>/DpTest",
      "run_type": "iteration",
      "repetitions": 0,
      "repetition_index": 2,
      "threads": 1,
      "iterations": 1,
      "real_time": 3.3689301220021000e+13,
      "cpu_time": 1.0524639260500000e+11,
      "time_unit": "ns",
      "elapsed": 3.5446122881999997e+01
    },
    {
      "name": "MyFixture<double>/DpTest_mean",
      "run_name": "MyFixture<double>/DpTest",
      "run_type": "aggregate",
      "repetitions": 0,
      "threads": 1,
      "aggregate_name": "mean",
      "iterations": 3,
      "real_time": 3.3653497522820996e+13,
      "cpu_time": 6.9443550779999985e+10,
      "time_unit": "ns",
      "elapsed": 3.5076749360666668e+01
    },
    {
      "name": "MyFixture<double>/DpTest_median",
      "run_name": "MyFixture<double>/DpTest",
      "run_type": "aggregate",
      "repetitions": 0,
      "threads": 1,
      "aggregate_name": "median",
      "iterations": 3,
      "real_time": 3.3653850476522000e+13,
      "cpu_time": 6.9796243118000015e+10,
      "time_unit": "ns",
      "elapsed": 3.5446122881999997e+01
    },
    {
      "name": "MyFixture<double>/DpTest_stddev",
      "run_name": "MyFixture<double>/DpTest",
      "run_type": "aggregate",
      "repetitions": 0,
      "threads": 1,
      "aggregate_name": "stddev",
      "iterations": 3,
      "real_time": 3.5981472413457527e+10,
      "cpu_time": 3.5980484468966743e+10,
      "time_unit": "ns",
      "elapsed": 1.6441472661615966e+00
    },
    {
      "name": "MyFixture<double>/RecursionTest",
      "run_name": "MyFixture<double>/RecursionTest",
      "run_type": "iteration",
      "repetitions": 0,
      "repetition_index": 0,
      "threads": 1,
      "iterations": 1,
      "real_time": 3.3712641641272996e+13,
      "cpu_time": 1.2858756744700003e+11,
      "time_unit": "ns",
      "elapsed": 2.3335830585000000e+01
    },
    {
      "name": "MyFixture<double>/RecursionTest",
      "run_name": "MyFixture<double>/RecursionTest",
      "run_type": "iteration",
      "repetitions": 0,
      "repetition_index": 1,
      "threads": 1,
      "iterations": 1,
      "real_time": 3.3736140685774000e+13,
      "cpu_time": 1.5208737819100003e+11,
      "time_unit": "ns",
      "elapsed": 2.3495174519999999e+01
    },
    {
      "name": "MyFixture<double>/RecursionTest",
      "run_name": "MyFixture<double>/RecursionTest",
      "run_type": "iteration",
      "repetitions": 0,
      "repetition_index": 2,
      "threads": 1,
      "iterations": 1,
      "real_time": 3.3759810651286004e+13,
      "cpu_time": 1.7575816677000000e+11,
      "time_unit": "ns",
      "elapsed": 2.3665932091999998e+01
    },
    {
      "name": "MyFixture<double>/RecursionTest_mean",
      "run_name": "MyFixture<double>/RecursionTest",
      "run_type": "aggregate",
      "repetitions": 0,
      "threads": 1,
      "aggregate_name": "mean",
      "iterations": 3,
      "real_time": 3.3736197659444332e+13,
      "cpu_time": 1.5214437080266669e+11,
      "time_unit": "ns",
      "elapsed": 2.3498979065666664e+01
    },
    {
      "name": "MyFixture<double>/RecursionTest_median",
      "run_name": "MyFixture<double>/RecursionTest",
      "run_type": "aggregate",
      "repetitions": 0,
      "threads": 1,
      "aggregate_name": "median",
      "iterations": 3,
      "real_time": 3.3736140685774000e+13,
      "cpu_time": 1.5208737819100003e+11,
      "time_unit": "ns",
      "elapsed": 2.3495174519999999e+01
    },
    {
      "name": "MyFixture<double>/RecursionTest_stddev",
      "run_name": "MyFixture<double>/RecursionTest",
      "run_type": "aggregate",
      "repetitions": 0,
      "threads": 1,
      "aggregate_name": "stddev",
      "iterations": 3,
      "real_time": 2.3584556620034870e+10,
      "cpu_time": 2.3585351306289410e+10,
      "time_unit": "ns",
      "elapsed": 1.6508363685325447e-01
    },
    {
      "name": "MyFixture<double>/RecursionTest",
      "run_name": "MyFixture<double>/RecursionTest",
      "run_type": "iteration",
      "repetitions": 0,
      "repetition_index": 0,
      "threads": 1,
      "iterations": 1,
      "real_time": 3.3784076516954004e+13,
      "cpu_time": 2.0002486231600000e+11,
      "time_unit": "ns",
      "elapsed": 2.4261430826000002e+01
    },
    {
      "name": "MyFixture<double>/RecursionTest",
      "run_name": "MyFixture<double>/RecursionTest",
      "run_type": "iteration",
      "repetitions": 0,
      "repetition_index": 1,
      "threads": 1,
      "iterations": 1,
      "real_time": 3.3806799232876996e+13,
      "cpu_time": 2.2274835789400000e+11,
      "time_unit": "ns",
      "elapsed": 2.2718458892000001e+01
    },
    {
      "name": "MyFixture<double>/RecursionTest",
      "run_name": "MyFixture<double>/RecursionTest",
      "run_type": "iteration",
      "repetitions": 0,
      "repetition_index": 2,
      "threads": 1,
      "iterations": 1,
      "real_time": 3.3829570009330004e+13,
      "cpu_time": 2.4552001596500000e+11,
      "time_unit": "ns",
      "elapsed": 2.2766313009000001e+01
    },
    {
      "name": "MyFixture<double>/RecursionTest_mean",
      "run_name": "MyFixture<double>/RecursionTest",
      "run_type": "aggregate",
      "repetitions": 0,
      "threads": 1,
      "aggregate_name": "mean",
      "iterations": 3,
      "real_time": 3.3806815253053660e+13,
      "cpu_time": 2.2276441205833334e+11,
      "time_unit": "ns",
      "elapsed": 2.3248734242333331e+01
    },
    {
      "name": "MyFixture<double>/RecursionTest_median",
      "run_name": "MyFixture<double>/RecursionTest",
      "run_type": "aggregate",
      "repetitions": 0,
      "threads": 1,
      "aggregate_name": "median",
      "iterations": 3,
      "real_time": 3.3806799232876996e+13,
      "cpu_time": 2.2274835789400000e+11,
      "time_unit": "ns",
      "elapsed": 2.2766313009000001e+01
    },
    {
      "name": "MyFixture<double>/RecursionTest_stddev",
      "run_name": "MyFixture<double>/RecursionTest",
      "run_type": "aggregate",
      "repetitions": 0,
      "threads": 1,
      "aggregate_name": "stddev",
      "iterations": 3,
      "real_time": 2.2746750426603119e+10,
      "cpu_time": 2.2747581073351292e+10,
      "time_unit": "ns",
      "elapsed": 8.7734729842642867e-01
    },
    {
      "name": "MyFixture<double>/DpTest",
      "run_name": "MyFixture<double>/DpTest",
      "run_type": "iteration",
      "repetitions": 0,
      "repetition_index": 0,
      "threads": 1,
      "iterations": 1,
      "real_time": 3.3863025575470004e+13,
      "cpu_time": 2.7897689665100000e+11,
      "time_unit": "ns",
      "elapsed": 3.3450772870000002e+01
    },
    {
      "name": "MyFixture<double>/DpTest",
      "run_name": "MyFixture<double>/DpTest",
      "run_type": "iteration",
      "repetitions": 0,
      "repetition_index": 1,
      "threads": 1,
      "iterations": 1,
      "real_time": 3.3896463453114004e+13,
      "cpu_time": 3.1241604983700000e+11,
      "time_unit": "ns",
      "elapsed": 3.3433491934999999e+01
    },
    {
      "name": "MyFixture<double>/DpTest",
      "run_name": "MyFixture<double>/DpTest",
      "run_type": "iteration",
      "repetitions": 0,
      "repetition_index": 2,
      "threads": 1,
      "iterations": 1,
      "real_time": 3.3931457428383000e+13,
      "cpu_time": 3.4740945898900000e+11,
      "time_unit": "ns",
      "elapsed": 3.4989332685000001e+01
    },
    {
      "name": "MyFixture<double>/DpTest_mean",
      "run_name": "MyFixture<double>/DpTest",
      "run_type": "aggregate",
      "repetitions": 0,
      "threads": 1,
      "aggregate_name": "mean",
      "iterations": 3,
      "real_time": 3.3896982152322340e+13,
      "cpu_time": 3.1293413515900000e+11,
      "time_unit": "ns",
      "elapsed": 3.3957865830000003e+01
    },
    {
      "name": "MyFixture<double>/DpTest_median",
      "run_name": "MyFixture<double>/DpTest",
      "run_type": "aggregate",
      "repetitions": 0,
      "threads": 1,
      "aggregate_name": "median",
      "iterations": 3,
      "real_time": 3.3896463453114004e+13,
      "cpu_time": 3.1241604983700006e+11,
      "time_unit": "ns",
      "elapsed": 3.3450772870000002e+01
    },
    {
      "name": "MyFixture<double>/DpTest_stddev",
      "run_name": "MyFixture<double>/DpTest",
      "run_type": "aggregate",
      "repetitions": 0,
      "threads": 1,
      "aggregate_name": "stddev",
      "iterations": 3,
      "real_time": 3.4218875053908840e+10,
      "cpu_time": 3.4219222760558567e+10,
      "time_unit": "ns",
      "elapsed": 8.9331828728666862e-01
    }
  ]
}
