{
  "context": {
    "date": "2019-05-20 17:34:11",
    "host_name": "redwan",
    "executable": "./T_ASE_Benchmark",
    "num_cpus": 8,
    "mhz_per_cpu": 3700,
    "cpu_scaling_enabled": true,
    "caches": [
      {
        "type": "Data",
        "level": 1,
        "size": 32000000,
        "num_sharing": 2
      },
      {
        "type": "Instruction",
        "level": 1,
        "size": 32000000,
        "num_sharing": 2
      },
      {
        "type": "Unified",
        "level": 2,
        "size": 256000000,
        "num_sharing": 2
      },
      {
        "type": "Unified",
        "level": 3,
        "size": 6144000000,
        "num_sharing": 8
      },
      {
        "type": "Unified",
        "level": 4,
        "size": 131072000000,
        "num_sharing": 8
      }
    ],
    "load_avg": [1.08,1.03,0.83],
    "library_build_type": "release"
  },
  "benchmarks": [
    {
      "name": "MyFixture<double>/DpTest",
      "run_name": "MyFixture<double>/DpTest",
      "run_type": "iteration",
      "repetitions": 0,
      "repetition_index": 0,
      "threads": 1,
      "iterations": 1,
      "real_time": 2.6226407248480000e+13,
      "cpu_time": 2.9219609490000000e+09,
      "time_unit": "ns",
      "elapsed": 2.9180036610000002e+00
    },
    {
      "name": "MyFixture<double>/DpTest",
      "run_name": "MyFixture<double>/DpTest",
      "run_type": "iteration",
      "repetitions": 0,
      "repetition_index": 1,
      "threads": 1,
      "iterations": 1,
      "real_time": 2.6229330245122000e+13,
      "cpu_time": 5.8450163290000000e+09,
      "time_unit": "ns",
      "elapsed": 2.9227184679999998e+00
    },
    {
      "name": "MyFixture<double>/DpTest",
      "run_name": "MyFixture<double>/DpTest",
      "run_type": "iteration",
      "repetitions": 0,
      "repetition_index": 2,
      "threads": 1,
      "iterations": 1,
      "real_time": 2.6232263508171004e+13,
      "cpu_time": 8.7783550780000000e+09,
      "time_unit": "ns",
      "elapsed": 2.9329884730000000e+00
    },
    {
      "name": "MyFixture<double>/DpTest_mean",
      "run_name": "MyFixture<double>/DpTest",
      "run_type": "aggregate",
      "repetitions": 0,
      "threads": 1,
      "aggregate_name": "mean",
      "iterations": 3,
      "real_time": 2.6229333667257672e+13,
      "cpu_time": 5.8484441186666670e+09,
      "time_unit": "ns",
      "elapsed": 2.9245702006666665e+00
    },
    {
      "name": "MyFixture<double>/DpTest_median",
      "run_name": "MyFixture<double>/DpTest",
      "run_type": "aggregate",
      "repetitions": 0,
      "threads": 1,
      "aggregate_name": "median",
      "iterations": 3,
      "real_time": 2.6229330245122004e+13,
      "cpu_time": 5.8450163290000000e+09,
      "time_unit": "ns",
      "elapsed": 2.9227184679999998e+00
    },
    {
      "name": "MyFixture<double>/DpTest_stddev",
      "run_name": "MyFixture<double>/DpTest",
      "run_type": "aggregate",
      "repetitions": 0,
      "threads": 1,
      "aggregate_name": "stddev",
      "iterations": 3,
      "real_time": 2.9281313005540414e+09,
      "cpu_time": 2.9281985692320995e+09,
      "time_unit": "ns",
      "elapsed": 7.6621036973930651e-03
    },
    {
      "name": "MyFixture<double>/RecursionTest",
      "run_name": "MyFixture<double>/RecursionTest",
      "run_type": "iteration",
      "repetitions": 0,
      "repetition_index": 0,
      "threads": 1,
      "iterations": 1,
      "real_time": 2.6234389982530000e+13,
      "cpu_time": 1.0904904369999998e+10,
      "time_unit": "ns",
      "elapsed": 2.1260005529999999e+00
    },
    {
      "name": "MyFixture<double>/RecursionTest",
      "run_name": "MyFixture<double>/RecursionTest",
      "run_type": "iteration",
      "repetitions": 0,
      "repetition_index": 1,
      "threads": 1,
      "iterations": 1,
      "real_time": 2.6236567002480004e+13,
      "cpu_time": 1.3081971133000002e+10,
      "time_unit": "ns",
      "elapsed": 2.1767162700000000e+00
    },
    {
      "name": "MyFixture<double>/RecursionTest",
      "run_name": "MyFixture<double>/RecursionTest",
      "run_type": "iteration",
      "repetitions": 0,
      "repetition_index": 2,
      "threads": 1,
      "iterations": 1,
      "real_time": 2.6238781644671004e+13,
      "cpu_time": 1.5296673526000000e+10,
      "time_unit": "ns",
      "elapsed": 2.2143426079999999e+00
    },
    {
      "name": "MyFixture<double>/RecursionTest_mean",
      "run_name": "MyFixture<double>/RecursionTest",
      "run_type": "aggregate",
      "repetitions": 0,
      "threads": 1,
      "aggregate_name": "mean",
      "iterations": 3,
      "real_time": 2.6236579543227000e+13,
      "cpu_time": 1.3094516343000000e+10,
      "time_unit": "ns",
      "elapsed": 2.1723531436666663e+00
    },
    {
      "name": "MyFixture<double>/RecursionTest_median",
      "run_name": "MyFixture<double>/RecursionTest",
      "run_type": "aggregate",
      "repetitions": 0,
      "threads": 1,
      "aggregate_name": "median",
      "iterations": 3,
      "real_time": 2.6236567002480000e+13,
      "cpu_time": 1.3081971133000000e+10,
      "time_unit": "ns",
      "elapsed": 2.1767162700000000e+00
    },
    {
      "name": "MyFixture<double>/RecursionTest_stddev",
      "run_name": "MyFixture<double>/RecursionTest",
      "run_type": "aggregate",
      "repetitions": 0,
      "threads": 1,
      "aggregate_name": "stddev",
      "iterations": 3,
      "real_time": 2.1958579882396402e+09,
      "cpu_time": 2.1959114546398950e+09,
      "time_unit": "ns",
      "elapsed": 4.4332350760544766e-02
    },
    {
      "name": "MyFixture<double>/RecursionTest",
      "run_name": "MyFixture<double>/RecursionTest",
      "run_type": "iteration",
      "repetitions": 0,
      "repetition_index": 0,
      "threads": 1,
      "iterations": 1,
      "real_time": 2.6240929885406004e+13,
      "cpu_time": 1.7444979856000004e+10,
      "time_unit": "ns",
      "elapsed": 2.1477862790000000e+00
    },
    {
      "name": "MyFixture<double>/RecursionTest",
      "run_name": "MyFixture<double>/RecursionTest",
      "run_type": "iteration",
      "repetitions": 0,
      "repetition_index": 1,
      "threads": 1,
      "iterations": 1,
      "real_time": 2.6243061511776000e+13,
      "cpu_time": 1.9576674349000000e+10,
      "time_unit": "ns",
      "elapsed": 2.1313375589999999e+00
    },
    {
      "name": "MyFixture<double>/RecursionTest",
      "run_name": "MyFixture<double>/RecursionTest",
      "run_type": "iteration",
      "repetitions": 0,
      "repetition_index": 2,
      "threads": 1,
      "iterations": 1,
      "real_time": 2.6245217237806000e+13,
      "cpu_time": 2.1732433832000000e+10,
      "time_unit": "ns",
      "elapsed": 2.1554286860000000e+00
    },
    {
      "name": "MyFixture<double>/RecursionTest_mean",
      "run_name": "MyFixture<double>/RecursionTest",
      "run_type": "aggregate",
      "repetitions": 0,
      "threads": 1,
      "aggregate_name": "mean",
      "iterations": 3,
      "real_time": 2.6243069544996000e+13,
      "cpu_time": 1.9584696012333332e+10,
      "time_unit": "ns",
      "elapsed": 2.1448508413333336e+00
    },
    {
      "name": "MyFixture<double>/RecursionTest_median",
      "run_name": "MyFixture<double>/RecursionTest",
      "run_type": "aggregate",
      "repetitions": 0,
      "threads": 1,
      "aggregate_name": "median",
      "iterations": 3,
      "real_time": 2.6243061511776000e+13,
      "cpu_time": 1.9576674349000000e+10,
      "time_unit": "ns",
      "elapsed": 2.1477862790000000e+00
    },
    {
      "name": "MyFixture<double>/RecursionTest_stddev",
      "run_name": "MyFixture<double>/RecursionTest",
      "run_type": "aggregate",
      "repetitions": 0,
      "threads": 1,
      "aggregate_name": "stddev",
      "iterations": 3,
      "real_time": 2.1436875565000935e+09,
      "cpu_time": 2.1437382441407416e+09,
      "time_unit": "ns",
      "elapsed": 1.2310897438884990e-02
    },
    {
      "name": "MyFixture<double>/DpTest",
      "run_name": "MyFixture<double>/DpTest",
      "run_type": "iteration",
      "repetitions": 0,
      "repetition_index": 0,
      "threads": 1,
      "iterations": 1,
      "real_time": 2.6248145383069996e+13,
      "cpu_time": 2.4660661971000000e+10,
      "time_unit": "ns",
      "elapsed": 2.9277257390000000e+00
    },
    {
      "name": "MyFixture<double>/DpTest",
      "run_name": "MyFixture<double>/DpTest",
      "run_type": "iteration",
      "repetitions": 0,
      "repetition_index": 1,
      "threads": 1,
      "iterations": 1,
      "real_time": 2.6251078477228000e+13,
      "cpu_time": 2.7593828830000004e+10,
      "time_unit": "ns",
      "elapsed": 2.9328203099999999e+00
    },
    {
      "name": "MyFixture<double>/DpTest",
      "run_name": "MyFixture<double>/DpTest",
      "run_type": "iteration",
      "repetitions": 0,
      "repetition_index": 2,
      "threads": 1,
      "iterations": 1,
      "real_time": 2.6254024646512000e+13,
      "cpu_time": 3.0540084726000000e+10,
      "time_unit": "ns",
      "elapsed": 2.9458927259999999e+00
    },
    {
      "name": "MyFixture<double>/DpTest_mean",
      "run_name": "MyFixture<double>/DpTest",
      "run_type": "aggregate",
      "repetitions": 0,
      "threads": 1,
      "aggregate_name": "mean",
      "iterations": 3,
      "real_time": 2.6251082835603332e+13,
      "cpu_time": 2.7598191842333332e+10,
      "time_unit": "ns",
      "elapsed": 2.9354795916666667e+00
    },
    {
      "name": "MyFixture<double>/DpTest_median",
      "run_name": "MyFixture<double>/DpTest",
      "run_type": "aggregate",
      "repetitions": 0,
      "threads": 1,
      "aggregate_name": "median",
      "iterations": 3,
      "real_time": 2.6251078477227996e+13,
      "cpu_time": 2.7593828830000000e+10,
      "time_unit": "ns",
      "elapsed": 2.9328203099999999e+00
    },
    {
      "name": "MyFixture<double>/DpTest_stddev",
      "run_name": "MyFixture<double>/DpTest",
      "run_type": "aggregate",
      "repetitions": 0,
      "threads": 1,
      "aggregate_name": "stddev",
      "iterations": 3,
      "real_time": 2.9396341768694057e+09,
      "cpu_time": 2.9397138057828355e+09,
      "time_unit": "ns",
      "elapsed": 9.3708958163469351e-03
    }
  ]
}
